planchet/__init__.py
planchet/client.py
planchet/util.py
planchet-0.4.0.dist-info/LICENSE
planchet-0.4.0.dist-info/METADATA
planchet-0.4.0.dist-info/WHEEL
planchet-0.4.0.dist-info/top_level.txt
planchet-0.4.0.dist-info/zip-safe
planchet-0.4.0.dist-info/RECORD
