Metadata-Version: 2.1
Name: planchet
Version: 0.4.0
Summary: Large Data Processing Assistant
Home-page: UNKNOWN
Author: Sasho Savkov
License: MIT
Platform: UNKNOWN
Classifier: Intended Audience :: Developers
Classifier: Operating System :: OS Independent
Classifier: Programming Language :: Python
Classifier: Programming Language :: Python :: 3.6
Classifier: Topic :: Internet :: WWW/HTTP
Requires-Dist: requests (==2.23.0)
